elasticsearch/__init__.py
elasticsearch/compat.py
elasticsearch/connection_pool.py
elasticsearch/exceptions.py
elasticsearch/serializer.py
elasticsearch/transport.py
elasticsearch/client/__init__.py
elasticsearch/client/cat.py
elasticsearch/client/cluster.py
elasticsearch/client/indices.py
elasticsearch/client/ingest.py
elasticsearch/client/nodes.py
elasticsearch/client/snapshot.py
elasticsearch/client/tasks.py
elasticsearch/client/utils.py
elasticsearch/connection/__init__.py
elasticsearch/connection/base.py
elasticsearch/connection/http_requests.py
elasticsearch/connection/http_urllib3.py
elasticsearch/connection/pooling.py
elasticsearch/helpers/__init__.py
elasticsearch/helpers/test.py
elasticsearch2/__init__.py
elasticsearch2/compat.py
elasticsearch2/connection_pool.py
elasticsearch2/exceptions.py
elasticsearch2/serializer.py
elasticsearch2/transport.py
elasticsearch2/client/__init__.py
elasticsearch2/client/cat.py
elasticsearch2/client/cluster.py
elasticsearch2/client/indices.py
elasticsearch2/client/nodes.py
elasticsearch2/client/snapshot.py
elasticsearch2/client/tasks.py
elasticsearch2/client/utils.py
elasticsearch2/connection/__init__.py
elasticsearch2/connection/base.py
elasticsearch2/connection/http_requests.py
elasticsearch2/connection/http_urllib3.py
elasticsearch2/connection/pooling.py
elasticsearch2/helpers/__init__.py
elasticsearch2/helpers/test.py
elasticsearch2-2.5.0.dist-info/DESCRIPTION.rst
elasticsearch2-2.5.0.dist-info/METADATA
elasticsearch2-2.5.0.dist-info/RECORD
elasticsearch2-2.5.0.dist-info/WHEEL
elasticsearch2-2.5.0.dist-info/metadata.json
elasticsearch2-2.5.0.dist-info/top_level.txt
